timelocked/__init__.py
timelocked/main.py
timelocked-0.1.0.dist-info/METADATA
timelocked-0.1.0.dist-info/WHEEL
timelocked-0.1.0.dist-info/entry_points.txt
timelocked-0.1.0.dist-info/top_level.txt
timelocked-0.1.0.dist-info/RECORD
