Metadata-Version: 2.4
Name: timelocked
Version: 0.1.0
Summary: Record the amount of time that a machine is locked or unlocked for
Author-email: readwithai <talwrii@gmail.com>
Requires-Python: >=3.10
